fastapi_profiler/__init__.py
fastapi_profiler/dashboard.py
fastapi_profiler/instrumentations/__init__.py
fastapi_profiler/instrumentations/base.py
fastapi_profiler/instrumentations/sqlalchemy.py
fastapi_profiler/middleware.py
fastapi_profiler/profiler.py
fastapi_profiler/rustcore/Cargo.lock
fastapi_profiler/rustcore/Cargo.toml
fastapi_profiler/rustcore/__init__.py
fastapi_profiler/rustcore/build.sh
fastapi_profiler/rustcore/pyproject.toml
fastapi_profiler/rustcore/setup.py
fastapi_profiler/rustcore/src/lib.rs
fastapi_profiler/rustcore/src/stats_aggregator.rs
fastapi_profiler/rustcore/target/CACHEDIR.TAG
fastapi_profiler/rustcore/target/release/.cargo-lock
fastapi_profiler/static/__init__.py
fastapi_profiler/static/css/styles.css
fastapi_profiler/static/js/dashboard.js
fastapi_profiler/static/templates/dashboard.html
fastapi_profiler/stats.py
fastapi_profiler/utils.py
fastapi_profiler_lite-0.3.3.dist-info/LICENSE
fastapi_profiler_lite-0.3.3.dist-info/METADATA
fastapi_profiler_lite-0.3.3.dist-info/WHEEL
fastapi_profiler_lite-0.3.3.dist-info/RECORD
