Metadata-Version: 2.1
Name: fastapi-profiler-lite
Version: 0.3.3
Summary: Lightweight performance profiler for FastAPI applications
Home-page: https://github.com/al91liwo/fastapi-profiler
License: MIT
Keywords: fastapi,profiler,performance,monitoring,lightweight,rust
Author: Alexander Lind
Author-email: al91liwo@gmail.com
Requires-Python: >=3.8,<4.0
Classifier: Framework :: FastAPI
Classifier: License :: OSI Approved :: MIT License
Classifier: Operating System :: OS Independent
Classifier: Programming Language :: Python :: 3
Classifier: Programming Language :: Python :: 3.8
Classifier: Programming Language :: Python :: 3.9
Classifier: Programming Language :: Python :: 3.10
Classifier: Programming Language :: Python :: 3.11
Classifier: Topic :: Software Development :: Debuggers
Classifier: Topic :: Software Development :: Libraries :: Python Modules
Provides-Extra: all
Provides-Extra: database
Provides-Extra: webserver
Requires-Dist: fastapi (>=0.68.0)
Requires-Dist: fastapi-profiler-rust (>=0.3.2)
Requires-Dist: jinja2 (>=3.1.2)
Requires-Dist: sqlalchemy (>=1.4.0) ; extra == "database" or extra == "all"
Requires-Dist: sqlparse (>=0.5.3,<0.6.0) ; extra == "database" or extra == "all"
Requires-Dist: starlette (>=0.14.2)
Requires-Dist: uvicorn (>=0.14.0) ; extra == "webserver" or extra == "all"
Project-URL: Documentation, https://github.com/al91liwo/fastapi-profiler/tree/main/docs
Project-URL: Repository, https://github.com/al91liwo/fastapi-profiler
